Workbook

Sheet 價值股Top10
A1: 排名 | B1: 代號 | C1: 公司 | D1: 市場 | E1: 產業 | F1: 發行股數(百萬股) | G1: 收盤價(10/16) | H1: 市值(億元) | I1: 52週低點 | J1: 低點日期 | K1: 距低點% | L1: 近四季EPS(元) | M1: TTM P/E | N1: P/B | O1: 殖利率% | P1: 營收月份 | Q1: 近月營收年增率 | R1: 累計營收年增率 | S1: 上半年EPS年增率 | T1: 近四季營業現金流(億) | U1: 近四季自由現金流(億) | V1: 負債比 | W1: ROE(上半年年化) | X1: 20日均量(張) | Y1: 價值評分 | Z1: 投資論點（分析判斷） | AA1: 催化劑（分析判斷） | AB1: 主要風險（分析判斷）
A2: 1 | B2: 2204 | C2: 中華 | D2: 上市 | E2: 汽車工業 | F2: 553.62 | G2: 53 | H2: =F2*G2/100 -> 293.4186 | I2: 50 | J2: 2026/08/04 | K2: =G2/I2-1 -> 0.06 | L2: =SUM(季資料!C2:F2) -> 6.21 | M2: =G2/L2 -> 8.5346216 | N2: 0.77 | O2: 0.0679 | P2: 115/09 | Q2: 0.041655447 | R2: 0.085320925 | S2: =SUM(季資料!C2:D2)/SUM(季資料!G2:H2)-1 -> 0.31687243 | T2: =SUM(季資料!I2:L2)/100000 -> 17.50375 | U2: =SUM(季資料!M2:P2)/100000 -> 13.69331 | V2: 0.2401755 | W2: 0.09089614 | X2: 596 | Y2: 85.6 | Z2: 本益比約 8.5 倍、淨值比 0.77、殖利率 6.8%，估值在名單中最便宜之一；負債比 24%、近四季自由現金流為正 | AA2: Q2 EPS 2.02 元、年增 58%，若下半年維持，近四季 EPS 可續升 | AB2: 汽車業景氣循環；Q1 營業現金流為負，現金流季度波動大
A3: 2 | B3: 1307 | C3: 三芳 | D3: 上市 | E3: 塑膠工業 | F3: 397.82 | G3: 31.45 | H3: =F3*G3/100 -> 125.11439 | I3: 30 | J3: 2025/10/17 | K3: =G3/I3-1 -> 0.048333333 | L3: =SUM(季資料!C3:F3) -> 3.35 | M3: =G3/L3 -> 9.3880597 | N3: 1.26 | O3: 0.07 | P3: 115/09 | Q3: 0.0016969088 | R3: 0.056727297 | S3: =SUM(季資料!C3:D3)/SUM(季資料!G3:H3)-1 -> 0.52083333 | T3: =SUM(季資料!I3:L3)/100000 -> 8.40238 | U3: =SUM(季資料!M3:P3)/100000 -> 0.07797 | V3: 0.46716272 | W3: 0.11672306 | X3: 532 | Y3: 81.1 | Z3: 本益比約 9.4 倍、殖利率 7.0%；負債比 47%，近四季營業現金流為正 | AA3: 上半年 EPS 年增 52%（去年 Q2 有虧損，基期低） | AB3: Q2 EPS 季減 49%、Q2 營業現金流為負；近四季自由現金流僅約打平
A4: 3 | B4: 2504 | C4: 國產 | D4: 上市 | E4: 建材營造 | F4: 1180 | G4: 32 | H4: =F4*G4/100 -> 377.6 | I4: 30.15 | J4: 2026/08/07 | K4: =G4/I4-1 -> 0.061359867 | L4: =SUM(季資料!C4:F4) -> 3.19 | M4: =G4/L4 -> 10.031348 | N4: 1.45 | O4: 0.0813 | P4: 115/09 | Q4: -0.022893859 | R4: -0.075472923 | S4: =SUM(季資料!C4:D4)/SUM(季資料!G4:H4)-1 -> -0.069620253 | T4: =SUM(季資料!I4:L4)/100000 -> 51.50165 | U4: =SUM(季資料!M4:P4)/100000 -> 7.77839 | V4: 0.46077426 | W4: 0.13387561 | X4: 1671 | Y4: 75 | Z4: 本益比約 10 倍、殖利率 8.1%（名單最高）；近四季營業現金流 51.5 億、自由現金流為正 | AA4: 近四季營業現金流穩定為正（每季都 > 0），可留意下一次配息政策 | AB4: 營建／建材景氣與房市政策；高殖利率需確認配息能否維持
A5: 4 | B5: 1210 | C5: 大成 | D5: 上市 | E5: 食品工業 | F5: 894.77 | G5: 51.7 | H5: =F5*G5/100 -> 462.59609 | I5: 50.2 | J5: 2026/03/06 | K5: =G5/I5-1 -> 0.029880478 | L5: =SUM(季資料!C5:F5) -> 4.06 | M5: =G5/L5 -> 12.73399 | N5: 1.69 | O5: 0.058 | P5: 115/09 | Q5: 0.13154914 | R5: 0.095243221 | S5: =SUM(季資料!C5:D5)/SUM(季資料!G5:H5)-1 -> -0.15028902 | T5: =SUM(季資料!I5:L5)/100000 -> 64.67303 | U5: =SUM(季資料!M5:P5)/100000 -> -6.17491 | V5: 0.55780022 | W5: 0.096759928 | X5: 1145 | Y5: 74.2 | Z5: 本益比約 12.7 倍、殖利率 5.8%；近四季營業現金流 64.7 億 | AA5: 9 月營收年增 13% | AB5: 上半年 EPS 年減 15%、近兩季 EPS 都是年減；近四季自由現金流為負（投資支出大）
A6: 5 | B6: 9958 | C6: 世紀鋼 | D6: 上市 | E6: 鋼鐵工業 | F6: 266.9 | G6: 87.4 | H6: =F6*G6/100 -> 233.2706 | I6: 87.3 | J6: 2026/09/04 | K6: =G6/I6-1 -> 0.0011454754 | L6: =SUM(季資料!C6:F6) -> 7.02 | M6: =G6/L6 -> 12.450142 | N6: 1.83 | O6: 0.0515 | P6: 115/09 | Q6: 0.83327048 | R6: 0.45590949 | S6: =SUM(季資料!C6:D6)/SUM(季資料!G6:H6)-1 -> 0.13333333 | T6: =SUM(季資料!I6:L6)/100000 -> 39.16449 | U6: =SUM(季資料!M6:P6)/100000 -> -75.44982 | V6: 0.56424671 | W6: 0.1710243 | X6: 1358 | Y6: 72.7 | Z6: 股價幾乎貼著 52 週低點（距 0.1%），本益比約 12.4 倍、ROE 17% | AA6: 9 月營收年增 83%，可留意 Q3 財報是否反映 | AB6: Q2 投資現金流 -93.7 億，近四季自由現金流 -75 億；Q2 EPS 年減 34%，單季獲利波動大
A7: 6 | B7: 9904 | C7: 寶成 | D7: 上市 | E7: 運動休閒 | F7: 2946.79 | G7: 26.5 | H7: =F7*G7/100 -> 780.89935 | I7: 23.3 | J7: 2026/08/06 | K7: =G7/I7-1 -> 0.13733906 | L7: =SUM(季資料!C7:F7) -> 4.71 | M7: =G7/L7 -> 5.626327 | N7: 0.42 | O7: 0.0491 | P7: 115/09 | Q7: 0.10402545 | R7: -0.0051541163 | S7: =SUM(季資料!C7:D7)/SUM(季資料!G7:H7)-1 -> 0.35428571 | T7: =SUM(季資料!I7:L7)/100000 -> 144.09395 | U7: =SUM(季資料!M7:P7)/100000 -> -17.14168 | V7: 0.34130713 | W7: 0.074676357 | X7: 13381 | Y7: 68.2 | Z7: 本益比約 5.6 倍、淨值比 0.42，估值極低；近四季營業現金流 144 億 | AA7: Q2 EPS 1.61 元、年增 204% | AB7: 距 52 週低點 13.7%，接近上限；現金流資料只更新到 2026Q1，Q1 營業現金流為負
A8: 7 | B8: 1722 | C8: 台肥 | D8: 上市 | E8: 化學工業 | F8: 980 | G8: 42.1 | H8: =F8*G8/100 -> 412.58 | I8: 40.85 | J8: 2026/10/05 | K8: =G8/I8-1 -> 0.030599755 | L8: =SUM(季資料!C8:F8) -> 0.84 | M8: =G8/L8 -> 50.119048 | N8: 0.78 | O8: 0.0475 | P8: 115/09 | Q8: 0.069699862 | R8: 0.048585215 | S8: =SUM(季資料!C8:D8)/SUM(季資料!G8:H8)-1 -> -0.2037037 | T8: =SUM(季資料!I8:L8)/100000 -> 18.33994 | U8: =SUM(季資料!M8:P8)/100000 -> -3.08974 | V8: 0.36326649 | W8: 0.015813474 | X8: 2454 | Y8: 60.6 | Z8: 淨值比 0.78、殖利率 4.8%，資產面便宜 | AA8: 上半年 EPS 已轉正（Q1 0.19、Q2 0.24 元） | AB8: 本益比約 50 倍，以獲利衡量並不便宜；2025Q4 曾虧損，獲利基礎薄
A9: 8 | B9: 3413 | C9: 京鼎 | D9: 上市 | E9: 半導體業 | F9: 110.92 | G9: 281 | H9: =F9*G9/100 -> 311.6852 | I9: 271.5 | J9: 2026/09/14 | K9: =G9/I9-1 -> 0.034990792 | L9: =SUM(季資料!C9:F9) -> 20.28 | M9: =G9/L9 -> 13.856016 | N9: 1.88 | O9: 0.0391 | P9: 115/09 | Q9: 0.14549109 | R9: 0.19321432 | S9: =SUM(季資料!C9:D9)/SUM(季資料!G9:H9)-1 -> -0.1215415 | T9: =SUM(季資料!I9:L9)/100000 -> 17.38182 | U9: =SUM(季資料!M9:P9)/100000 -> 5.81606 | V9: 0.40536118 | W9: 0.11889768 | X9: 611 | Y9: 59.8 | Z9: 本益比約 14 倍、殖利率 3.9%；負債比 41%、近四季自由現金流為正 | AA9: Q2 EPS 4.61 元、年增 35%、季增 8%，獲利止跌回升 | AB9: 半導體設備景氣循環；上半年 EPS 仍年減 12%
A10: 9 | B10: 2439 | C10: 美律 | D10: 上市 | E10: 通信網路業 | F10: 248.64 | G10: 81.5 | H10: =F10*G10/100 -> 202.6416 | I10: 74.4 | J10: 2026/09/09 | K10: =G10/I10-1 -> 0.095430108 | L10: =SUM(季資料!C10:F10) -> 5.46 | M10: =G10/L10 -> 14.92674 | N10: 1.21 | O10: 0.0501 | P10: 115/09 | Q10: 0.040594667 | R10: 0.067416808 | S10: =SUM(季資料!C10:D10)/SUM(季資料!G10:H10)-1 -> 0.06993007 | T10: =SUM(季資料!I10:L10)/100000 -> 2.22704 | U10: =SUM(季資料!M10:P10)/100000 -> -1.79209 | V10: 0.54439345 | W10: 0.045493943 | X10: 1770 | Y10: 59.1 | Z10: 本益比約 14.9 倍、淨值比 1.21、殖利率 5.0% | AA10: 9 月營收年增 4%，股價距 52 週低點 9.5% | AB10: 近兩季 EPS 連續季減（Q2 0.50 元）；近四季營業現金流僅 2.2 億、自由現金流為負
A11: 10 | B11: 4114 | C11: 健喬 | D11: 上櫃 | E11: 生技醫療業 | F11: 550.43 | G11: 30.3 | H11: =F11*G11/100 -> 166.78029 | I11: 28.75 | J11: 2026/07/29 | K11: =G11/I11-1 -> 0.053913043 | L11: =SUM(季資料!C11:F11) -> 1.61 | M11: =G11/L11 -> 18.819876 | N11: 1.76 | O11: 0.0544 | P11: 115/09 | Q11: 0.38692673 | R11: 0.27041316 | S11: =SUM(季資料!C11:D11)/SUM(季資料!G11:H11)-1 -> -0.10869565 | T11: =SUM(季資料!I11:L11)/100000 -> 3.84053 | U11: =SUM(季資料!M11:P11)/100000 -> -7.34378 | V11: 0.35407775 | W11: 0.099514849 | X11: 854 | Y11: 59.1 | Z11: 殖利率 5.4%、負債比 35%；9 月營收年增 39% | AA11: 營收成長若延續，有機會帶動 Q3 獲利 | AB11: 本益比約 18.7 倍偏高；近四季自由現金流 -7.3 億；Q2 營業現金流為負
A13: 注意：接近 52 週低點不等於買點；本表只是依條件篩出的研究名單，不構成投資建議。投資論點／催化劑／風險欄為根據表內數字的分析判斷，尚未查證新聞與法說內容。
A14: 藍字＝來源數字；黑字＝公式。詳細規則與來源見「篩選規則與來源」工作表。

Sheet 備選與剔除
A1: 【備選】通過所有條件、評分排第 11～13 名
A2: 排名 | B2: 代號 | C2: 公司 | D2: 市場 | E2: 產業 | F2: 發行股數(百萬股) | G2: 收盤價(10/16) | H2: 市值(億元) | I2: 52週低點 | J2: 低點日期 | K2: 距低點% | L2: 近四季EPS(元) | M2: TTM P/E | N2: P/B | O2: 殖利率% | P2: 營收月份 | Q2: 近月營收年增率 | R2: 累計營收年增率 | S2: 上半年EPS年增率 | T2: 近四季營業現金流(億) | U2: 近四季自由現金流(億) | V2: 負債比 | W2: ROE(上半年年化) | X2: 20日均量(張) | Y2: 價值評分 | Z2: 投資論點（分析判斷） | AA2: 催化劑（分析判斷） | AB2: 主要風險（分析判斷）
A3: 11 | B3: 1227 | C3: 佳格 | D3: 上市 | E3: 食品工業 | F3: 915.09 | G3: 28.5 | H3: =F3*G3/100 -> 260.80065 | I3: 27.45 | J3: 2026/10/06 | K3: =G3/I3-1 -> 0.038251366 | L3: =SUM(季資料!C12:F12) -> 1.6 | M3: =G3/L3 -> 17.8125 | N3: 1.42 | O3: 0.047 | P3: 115/09 | Q3: 0.086654623 | R3: 0.075733246 | S3: =SUM(季資料!C12:D12)/SUM(季資料!G12:H12)-1 -> 0.53846154 | T3: =SUM(季資料!I12:L12)/100000 -> 27.52165 | U3: =SUM(季資料!M12:P12)/100000 -> -1.86833 | V3: 0.40082355 | W3: 0.079870214 | X3: 777 | Y3: 58.3
A4: 12 | B4: 9910 | C4: 豐泰 | D4: 上市 | E4: 運動休閒 | F4: 987.48 | G4: 69.8 | H4: =F4*G4/100 -> 689.26104 | I4: 66.1 | J4: 2026/10/07 | K4: =G4/I4-1 -> 0.055975794 | L4: =SUM(季資料!C13:F13) -> 4.92 | M4: =G4/L4 -> 14.186992 | N4: 2.91 | O4: 0.0587 | P4: 115/09 | Q4: -0.047605768 | R4: -0.031349068 | S4: =SUM(季資料!C13:D13)/SUM(季資料!G13:H13)-1 -> -0.095238095 | T4: =SUM(季資料!I13:L13)/100000 -> 74.16166 | U4: =SUM(季資料!M13:P13)/100000 -> 54.60594 | V4: 0.51082165 | W4: 0.14272761 | X4: 1215 | Y4: 58.3
A5: 13 | B5: 1229 | C5: 聯華 | D5: 上市 | E5: 食品工業 | F5: 1831.88 | G5: 41.05 | H5: =F5*G5/100 -> 751.98674 | I5: 38 | J5: 2026/05/25 | K5: =G5/I5-1 -> 0.080263158 | L5: =SUM(季資料!C14:F14) -> 2.48 | M5: =G5/L5 -> 16.552419 | N5: 1.17 | O5: 0.0487 | P5: 115/09 | Q5: 0.021309781 | R5: -0.04908445 | S5: =SUM(季資料!C14:D14)/SUM(季資料!G14:H14)-1 -> -0.090909091 | T5: =SUM(季資料!I14:L14)/100000 -> 65.49555 | U5: =SUM(季資料!M14:P14)/100000 -> 48.55954 | V5: 0.20087736 | W5: 0.068976968 | X5: 2410 | Y5: 56.8
A7: 【剔除】數字條件都過，但上半年 EPS 年減超過 25%，視為「基本面明顯惡化」
A8: 代號 | B8: 公司 | C8: 剔除原因
A9: 9938 | B9: 百和 | C9: 上半年 EPS 年減 38%（0.49+0.87 vs 0.67+1.54），基本面明顯轉弱
A10: 7780 | B10: 大研生醫* | C10: 上半年 EPS 年減 88%（0.16+0.13 vs 0.65+1.75），基本面明顯轉弱

Sheet 季資料
A1: 代號 | B1: 公司 | C1: EPS 26Q2 | D1: EPS 26Q1 | E1: EPS 25Q4 | F1: EPS 25Q3 | G1: EPS 25Q2 | H1: EPS 25Q1 | I1: 營業CF 最新 | J1: 營業CF 前1季 | K1: 營業CF 前2季 | L1: 營業CF 前3季 | M1: 自由CF 最新 | N1: 自由CF 前1季 | O1: 自由CF 前2季 | P1: 自由CF 前3季 | Q1: 現金流最新季 | R1: 來源網址
A2: 2204 | B2: 中華 | C2: 2.02 | D2: 1.18 | E2: 1.54 | F2: 1.47 | G2: 1.28 | H2: 1.15 | I2: 946011 | J2: -188264 | K2: 784711 | L2: 207917 | M2: 534528 | N2: 72581 | O2: 262200 | P2: 500022 | Q2: 2026Q2 | R2: https://tw.stock.yahoo.com/quote/2204.TW/eps ； https://tw.stock.yahoo.com/quote/2204.TW/cash-flow-statement
A3: 1307 | B3: 三芳 | C3: 0.49 | D3: 0.97 | E3: 0.84 | F3: 1.05 | G3: -0.12 | H3: 1.08 | I3: -200898 | J3: 51391 | K3: 609135 | L3: 380610 | M3: -767190 | N3: 508692 | O3: 403028 | P3: -136733 | Q3: 2026Q2 | R3: https://tw.stock.yahoo.com/quote/1307.TW/eps ； https://tw.stock.yahoo.com/quote/1307.TW/cash-flow-statement
A4: 2504 | B4: 國產 | C4: 0.77 | D4: 0.7 | E4: 0.85 | F4: 0.87 | G4: 0.87 | H4: 0.71 | I4: 494248 | J4: 1361104 | K4: 1864337 | L4: 1430476 | M4: -481998 | N4: -20527 | O4: 644691 | P4: 635673 | Q4: 2026Q2 | R4: https://tw.stock.yahoo.com/quote/2504.TW/eps ； https://tw.stock.yahoo.com/quote/2504.TW/cash-flow-statement
A5: 1210 | B5: 大成 | C5: 0.53 | D5: 0.94 | E5: 1.66 | F5: 0.93 | G5: 0.68 | H5: 1.05 | I5: 678445 | J5: 2047783 | K5: 1530386 | L5: 2210689 | M5: -143911 | N5: -986303 | O5: -289745 | P5: 802468 | Q5: 2026Q2 | R5: https://tw.stock.yahoo.com/quote/1210.TW/eps ； https://tw.stock.yahoo.com/quote/1210.TW/cash-flow-statement
A6: 9958 | B6: 世紀鋼 | C6: 1.45 | D6: 2.63 | E6: 1.77 | F6: 1.17 | G6: 2.19 | H6: 1.41 | I6: 1322543 | J6: 576564 | K6: 844920 | L6: 1172422 | M6: -8043257 | N6: -1576311 | O6: 1910924 | P6: 163662 | Q6: 2026Q2 | R6: https://tw.stock.yahoo.com/quote/9958.TW/eps ； https://tw.stock.yahoo.com/quote/9958.TW/cash-flow-statement
A7: 9904 | B7: 寶成 | C7: 1.61 | D7: 0.76 | E7: 1.06 | F7: 1.28 | G7: 0.53 | H7: 1.22 | I7: -4393182 | J7: 4441191 | K7: 2368920 | L7: 11992466 | M7: -11422860 | N7: -1772485 | O7: -1797333 | P7: 13278510 | Q7: 2026Q1 | R7: https://tw.stock.yahoo.com/quote/9904.TW/eps ； https://tw.stock.yahoo.com/quote/9904.TW/cash-flow-statement
A8: 1722 | B8: 台肥 | C8: 0.24 | D8: 0.19 | E8: -0.16 | F8: 0.57 | G8: 0.44 | H8: 0.1 | I8: 70973 | J8: 226122 | K8: 1236237 | L8: 300662 | M8: -443915 | N8: -310531 | O8: 174366 | P8: 271106 | Q8: 2026Q2 | R8: https://tw.stock.yahoo.com/quote/1722.TW/eps ； https://tw.stock.yahoo.com/quote/1722.TW/cash-flow-statement
A9: 3413 | B9: 京鼎 | C9: 4.61 | D9: 4.28 | E9: 5.29 | F9: 6.1 | G9: 3.41 | H9: 6.71 | I9: -209372 | J9: 110652 | K9: 1188739 | L9: 648163 | M9: -131413 | N9: -569785 | O9: 648961 | P9: 633843 | Q9: 2026Q2 | R9: https://tw.stock.yahoo.com/quote/3413.TW/eps ； https://tw.stock.yahoo.com/quote/3413.TW/cash-flow-statement
A10: 2439 | B10: 美律 | C10: 0.5 | D10: 1.03 | E10: 1.6 | F10: 2.33 | G10: 0.01 | H10: 1.42 | I10: -1280201 | J10: 1431612 | K10: 44342 | L10: 26951 | M10: -891462 | N10: 1087771 | O10: -358448 | P10: -17070 | Q10: 2026Q2 | R10: https://tw.stock.yahoo.com/quote/2439.TW/eps ； https://tw.stock.yahoo.com/quote/2439.TW/cash-flow-statement
A11: 4114 | B11: 健喬 | C11: 0.44 | D11: 0.38 | E11: 0.38 | F11: 0.41 | G11: 0.44 | H11: 0.48 | I11: -78205 | J11: 269514 | K11: 185723 | L11: 7021 | M11: -720203 | N11: -149117 | O11: 1044356 | P11: -909414 | Q11: 2026Q2 | R11: https://tw.stock.yahoo.com/quote/4114.TWO/eps ； https://tw.stock.yahoo.com/quote/4114.TWO/cash-flow-statement
A12: 1227 | B12: 佳格 | C12: 0.28 | D12: 0.52 | E12: 0.39 | F12: 0.41 | G12: 0.13 | H12: 0.39 | I12: -235795 | J12: 416505 | K12: 1120212 | L12: 1451243 | M12: -2613351 | N12: 28378 | O12: 422811 | P12: 1975329 | Q12: 2026Q2 | R12: https://tw.stock.yahoo.com/quote/1227.TW/eps ； https://tw.stock.yahoo.com/quote/1227.TW/cash-flow-statement
A13: 9910 | B13: 豐泰 | C13: 1.03 | D13: 0.68 | E13: 1.45 | F13: 1.76 | G13: 0.73 | H13: 1.16 | I13: 1421786 | J13: -286708 | K13: 1910131 | L13: 4370957 | M13: 837368 | N13: -666515 | O13: 1337975 | P13: 3951766 | Q13: 2026Q2 | R13: https://tw.stock.yahoo.com/quote/9910.TW/eps ； https://tw.stock.yahoo.com/quote/9910.TW/cash-flow-statement
... A16: 7780 | B16: 大研生醫* | C16: 0.16 | D16: 0.13 | E16: 0.19 | F16: 1.06 | G16: 0.65 | H16: 1.75 | I16: 25437 | J16: 79485 | K16: 123048 | L16: 34630 | M16: -93282 | N16: 3084590 | O16: -1502793 | P16: -1366660 | Q16: 2026Q2 | R16: https://tw.stock.yahoo.com/quote/7780.TW/eps ； https://tw.stock.yahoo.com/quote/7780.TW/cash-flow-statement
A18: 單位：EPS 為元（單季）；現金流為仟元（單季）。自由現金流採 Yahoo 股市定義＝營業現金流＋投資現金流。9904 寶成的現金流網頁最新只到 2026Q1，所以它的 4 季是 2025Q2～2026Q1。

Sheet 篩選規則與來源
A1: 台股價值股初步名單：篩選規則、漏斗與資料來源
A2: 資料截至 | B2: 2026/10/16（週五）收盤；財報為 2026Q2；月營收為 2026 年 9 月
A4: 篩選條件（依序檢查） | B4: 門檻 | C4: 刷掉檔數
A5: 只看上市櫃普通股、有收盤價與股數 | B5: 4 碼、非 0 開頭 | C5: 37
A6: 市值 | B6: ≥ 100 億元 | C6: 1261
A7: 處置股／變更交易（全額交割） | B7: 排除 | C7: 6
A8: 股價歷史 | B8: 52 週內至少 150 個交易日 | C8: 9
A9: 距 52 週低點 | B9: ≤ 15% | C9: 506
A10: 流動性 | B10: 近 20 日均量 ≥ 500 張 | C10: 80
A11: 近四季 EPS | B11: > 0（本益比有值） | C11: 6
A12: 負債比（一般產業） | B12: ≤ 60% | C12: 24
A13: 金融股（銀行、保險、證券、金控） | B13: 改看 ROE > 8%（上半年淨利×2 ÷ 母公司權益） | C13: 6
A14: 今年上半年 EPS | B14: > 0 | C14: 2
A15: 營收 | B15: 9 月年增率與累計年增率都 ≥ -10% | C15: 12
A16: 毛利率（一般產業） | B16: 最近一季 > 0 | C16: 0
A17: → 通過以上條件 | C17: 34 檔
A18: 近四季營業現金流或自由現金流 | B18: > 0（逐檔查 Yahoo 股市，查了評分前 15 名） | C18: 0 檔被刷掉
A19: 上半年 EPS 年增率（明顯惡化判斷） | B19: ≥ -25% | C19: 2 檔（見「備選與剔除」）
A20: → 排序 | B20: 價值評分（本益比低、淨值比低、殖利率高、離低點近，四項百分位平均） | C20: 取前 10 名
A22: 資料來源
A23: 上市每日收盤行情（52 週高低、均量） | B23: https://www.twse.com.tw/rwd/zh/afterTrading/MI_INDEX?date=YYYYMMDD&type=ALLBUT0999&response=json
A24: 上市 10/16 行情 | B24: https://openapi.twse.com.tw/v1/exchangeReport/STOCK_DAY_ALL
A25: 上市本益比／殖利率／淨值比 | B25: https://openapi.twse.com.tw/v1/exchangeReport/BWIBBU_ALL
A26: 上市公司基本資料（發行股數） | B26: https://openapi.twse.com.tw/v1/opendata/t187ap03_L
A27: 上市月營收 | B27: https://openapi.twse.com.tw/v1/opendata/t187ap05_L
A28: 上市綜合損益表／資產負債表 | B28: https://openapi.twse.com.tw/v1/opendata/t187ap06_L_ci （及 _basi/_bd/_fh/_ins/_mim）；t187ap07_L_*
A29: 上市營益分析（毛利率） | B29: https://openapi.twse.com.tw/v1/opendata/t187ap17_L
A30: 上市處置股／變更交易 | B30: https://openapi.twse.com.tw/v1/announcement/punish ； https://openapi.twse.com.tw/v1/exchangeReport/TWT85U
A31: 上櫃每日收盤行情 | B31: https://www.tpex.org.tw/www/zh-tw/afterTrading/otc?date=YYYY/MM/DD&type=EW&response=json
A32: 上櫃行情／本益比 | B32: https://www.tpex.org.tw/openapi/v1/tpex_mainboard_quotes ； https://www.tpex.org.tw/openapi/v1/tpex_mainboard_peratio_analysis
A33: 上櫃基本資料／月營收／財報 | B33: https://www.tpex.org.tw/openapi/v1/mopsfin_t187ap03_O ； mopsfin_t187ap05_O ； mopsfin_t187ap06_O_* ； mopsfin_t187ap07_O_*
A34: 上櫃處置股 | B34: https://www.tpex.org.tw/openapi/v1/tpex_disposal_information
A35: 單季 EPS、現金流量（逐檔） | B35: https://tw.stock.yahoo.com/quote/代號.TW/eps ； https://tw.stock.yahoo.com/quote/代號.TW/cash-flow-statement（網址逐檔列在「季資料」）
A37: 已知限制
A38: 1 | B38: 公開資訊觀測站擋住雲端連線，現金流量改用 Yahoo 股市；Yahoo 的自由現金流定義＝營業＋投資現金流
A39: 2 | B39: 現金流與單季 EPS 只查了評分前 15 名；其餘 19 檔通過名單未逐檔檢查
A40: 3 | B40: 上櫃全額交割股沒有獨立清單，只排除了處置股
A41: 4 | B41: 9904 寶成 Yahoo 現金流只到 2026Q1
A42: 5 | B42: 投資論點／催化劑／風險只根據數字判斷，尚未查證新聞、法說會與除權息日程
